instantneo/__init__.py
instantneo/core.py
instantneo/adapters/__init__.py
instantneo/adapters/anthropic_adapter.py
instantneo/adapters/base_adapter.py
instantneo/adapters/groq_adapter.py
instantneo/adapters/openai_adapter.py
instantneo/skills/__init__.py
instantneo/skills/skill_decorators.py
instantneo/skills/skill_manager.py
instantneo/skills/skill_manager_operations.py
instantneo/utils/__init__.py
instantneo/utils/image_utils.py
instantneo/utils/skill_utils.py
instantneo-0.1.1.dist-info/licenses/LICENSE
instantneo-0.1.1.dist-info/METADATA
instantneo-0.1.1.dist-info/WHEEL
instantneo-0.1.1.dist-info/top_level.txt
instantneo-0.1.1.dist-info/RECORD
