Metadata-Version: 2.4
Name: instantneo
Version: 0.1.1
Home-page: https://github.com/dponcedeleonf/instantneo
Author: Diego Ponce de León Franco
Author-email: dponcedeleonf@gmail.com
Project-URL: Bug Reports, https://github.com/dponcedeleonf/instantneo/issues
Project-URL: Source, https://github.com/dponcedeleonf/instantneo
Keywords: openai,agent,wrapper
Classifier: Development Status :: 3 - Alpha
Classifier: Intended Audience :: Developers
Classifier: Programming Language :: Python :: 3
Classifier: Programming Language :: Python :: 3.11
License-File: LICENSE
Requires-Dist: docstring_parser
Provides-Extra: openai
Requires-Dist: openai; extra == "openai"
Provides-Extra: anthropic
Requires-Dist: anthropic; extra == "anthropic"
Provides-Extra: groq
Requires-Dist: groq; extra == "groq"
Provides-Extra: all
Requires-Dist: openai; extra == "all"
Requires-Dist: anthropic; extra == "all"
Requires-Dist: groq; extra == "all"
Dynamic: author
Dynamic: author-email
Dynamic: classifier
Dynamic: description
Dynamic: description-content-type
Dynamic: home-page
Dynamic: keywords
Dynamic: license-file
Dynamic: project-url
Dynamic: provides-extra
Dynamic: requires-dist
